example/__init__.py
example/consumer.py
example/producer.py
kafkatool/__init__.py
kafkatool/client/__init__.py
kafkatool/client/callbacks.py
kafkatool/client/consumer.py
kafkatool/client/producer.py
kafkatool/client/sede.py
kafkatool/client/utils.py
kafkatool/config/__init__.py
kafkatool/config/kconf.py
kafkatool/exception/__init__.py
kafkatool/metrics/__init__.py
kafkatool/metrics/counter.py
test/__init__.py
test/config.py
test/test_counter.py
test/test_kconf.py
test/test_producer.py
kafkatool-0.0.4.dist-info/LICENSE
kafkatool-0.0.4.dist-info/METADATA
kafkatool-0.0.4.dist-info/WHEEL
kafkatool-0.0.4.dist-info/top_level.txt
kafkatool-0.0.4.dist-info/RECORD
