Metadata-Version: 2.1
Name: kafkatool
Version: 0.0.4
Summary: kafkatool
Home-page: UNKNOWN
Author: xbzheng
Author-email: 
License: UNKNOWN
Platform: UNKNOWN
Classifier: Programming Language :: Python :: 3
Classifier: License :: OSI Approved :: MIT License
Classifier: Operating System :: OS Independent
Requires-Dist: confluent-kafka (>=0.11.6)
Requires-Dist: PyYAML (>=3.13)
Requires-Dist: structlog (>=18.2.0)
Requires-Dist: six (>=1.12.0)
